asm1_influent_generator/__init__.py
asm1_influent_generator/_version.py
asm1_influent_generator/asm1_generator.py
asm1_influent_generator/bsm2_dgan_model_230400iter.pt
asm1_influent_generator/skeleton.py
asm1_influent_generator-0.0.6.dist-info/METADATA
asm1_influent_generator-0.0.6.dist-info/WHEEL
asm1_influent_generator-0.0.6.dist-info/entry_points.txt
asm1_influent_generator-0.0.6.dist-info/licenses/AUTHORS.md
asm1_influent_generator-0.0.6.dist-info/licenses/LICENSE.txt
asm1_influent_generator-0.0.6.dist-info/RECORD
