Metadata-Version: 2.3
Name: asm1-influent-generator
Version: 0.0.6
Summary: A Python Module to generate Arrays in the Activated Sludge Model 1 (ASM1) format.
Project-URL: Documentation, https://gitlab.rrze.fau.de/evt/klaeffizient/asm1-influent-generator
Project-URL: Source, https://gitlab.rrze.fau.de/evt/klaeffizient/asm1-influent-generator
Author-email: Jonas Miederer <ttronas@live.de>
License: BSD-3-Clause
License-File: AUTHORS.md
License-File: LICENSE.txt
Keywords: ASM1,BSM2,activated sludge model,generator,influent,simulation,wastewater
Classifier: Development Status :: 2 - Pre-Alpha
Classifier: Programming Language :: Python
Classifier: Programming Language :: Python :: 3.9
Classifier: Programming Language :: Python :: 3.10
Classifier: Programming Language :: Python :: 3.11
Classifier: Programming Language :: Python :: Implementation :: CPython
Requires-Python: >=3.9
Requires-Dist: gretel-synthetics
Requires-Dist: numpy
Requires-Dist: torch
Requires-Dist: typer
